lerspy/__init__.py
lerspy/lers.py
lerspy-1.0.0.dist-info/METADATA
lerspy-1.0.0.dist-info/WHEEL
lerspy-1.0.0.dist-info/licenses/LICENSE
lerspy-1.0.0.dist-info/RECORD
