Metadata-Version: 2.1
Name: lerspy
Version: 1.0.0
Summary: Lightweight Enums, Rust-Styled! A package for Python featuring a custom interpretation of enumerations, heavily inspired by Rust's syntax and a focus on functionality + simplicity! 
Project-URL: Homepage, https://github.com/IAmNotIsaac/python-lers/tree/main
Project-URL: Bug Tracker, https://github.com/IAmNotIsaac/python-lers/issues
Author-email: Isaac Astell <isaacjulianastell@gmail.com>
License-File: LICENSE
Classifier: License :: OSI Approved :: MIT License
Classifier: Operating System :: OS Independent
Classifier: Programming Language :: Python :: 3
Requires-Python: >=3.11
